fontPens/__init__.py
fontPens/angledMarginPen.py
fontPens/digestPointPen.py
fontPens/flattenPen.py
fontPens/guessSmoothPointPen.py
fontPens/marginPen.py
fontPens/penTools.py
fontPens/printPen.py
fontPens/printPointPen.py
fontPens/recordingPointPen.py
fontPens/thresholdPen.py
fontPens/thresholdPointPen.py
fontPens/transformPointPen.py
fontPens-0.1.0.dist-info/DESCRIPTION.rst
fontPens-0.1.0.dist-info/LICENSE.txt
fontPens-0.1.0.dist-info/METADATA
fontPens-0.1.0.dist-info/RECORD
fontPens-0.1.0.dist-info/WHEEL
fontPens-0.1.0.dist-info/metadata.json
fontPens-0.1.0.dist-info/top_level.txt
