Metadata-Version: 2.0
Name: fontPens
Version: 0.1.0
Summary: A collection of classes implementing the pen protocol for manipulating glyphs.
Home-page: https://github.com/robofab-developers/fontPens
Author: Just van Rossum, Tal Leming, Erik van Blokland
Author-email: info@robofab.com
License: OpenSource, BSD-style
Platform: Any
Classifier: Development Status :: 4 - Beta
Classifier: Environment :: Console
Classifier: Environment :: Other Environment
Classifier: Intended Audience :: Developers
Classifier: Intended Audience :: End Users/Desktop
Classifier: License :: OSI Approved :: BSD License
Classifier: Natural Language :: English
Classifier: Operating System :: OS Independent
Classifier: Programming Language :: Python
Classifier: Topic :: Multimedia :: Graphics
Classifier: Topic :: Multimedia :: Graphics :: Graphics Conversion
Requires-Dist: fonttools (>=3.20.0)
Requires-Dist: ufoLib (>=2.0)
